libfuncpy/__init__.py
libfuncpy/lib.py
libfuncpy-0.0.4.dist-info/LICENSE
libfuncpy-0.0.4.dist-info/METADATA
libfuncpy-0.0.4.dist-info/WHEEL
libfuncpy-0.0.4.dist-info/entry_points.txt
libfuncpy-0.0.4.dist-info/top_level.txt
libfuncpy-0.0.4.dist-info/RECORD
