Metadata-Version: 2.1
Name: libfuncpy
Version: 0.0.4
Summary: Functional Programming tools in Python.
Home-page: https://github.com/joaomcteixeira/libfuncpy
Author: Joao Miguel Correia Teixeira
Author-email: joaomcteixeira@gmail.com
License: MIT License
Project-URL: webpage, https://github.com/joaomcteixeira/libfuncpy
Project-URL: Documentation, https://libfuncpy.readthedocs.io/en/latest/
Project-URL: Changelog, https://github.com/joaomcteixeira/libfuncpy/blob/main/docs/CHANGELOG.rst
Project-URL: Issue Tracker, https://github.com/joaomcteixeira/libfuncpy/issues
Project-URL: Discussion Forum, https://github.com/joaomcteixeira/libfuncpy/discussions
Keywords: functional programming
Platform: UNKNOWN
Classifier: Development Status :: 3 - Alpha
Classifier: License :: OSI Approved :: MIT License
Classifier: Natural Language :: English
Classifier: Operating System :: POSIX
Classifier: Operating System :: MacOS
Classifier: Operating System :: Microsoft
Classifier: Programming Language :: Python :: 3.6
Classifier: Programming Language :: Python :: 3.7
Classifier: Programming Language :: Python :: 3.8
Classifier: Programming Language :: Python :: 3.9
Requires-Python: >=3.6, <3.10
